Workbook
Name aporte: 'SIMULAÇÃO DE INVESTIMENTOS'!$D$17
Name patrimonio: 'SIMULAÇÃO DE INVESTIMENTOS'!$D$20
Name qntd_anos: 'SIMULAÇÃO DE INVESTIMENTOS'!$D$18
Name rendimento_carteira: 'SIMULAÇÃO DE INVESTIMENTOS'!$D$13
Name salario: 'SIMULAÇÃO DE INVESTIMENTOS'!$D$12
Name sugestao_investimento: 'SIMULAÇÃO DE INVESTIMENTOS'!$D$14
Name taxa_mensal: 'SIMULAÇÃO DE INVESTIMENTOS'!$D$19

Sheet SIMULAÇÃO DE INVESTIMENTOS
B11: CONFIGURAÇÕES
B12: Salário | D12: 2000
B13: Rendimento Carteira | D13: 0.006
B14: Sugestão de Investimento (30%) | D14: =D12*30% -> 600
B16: INVESTIMENTO MENSAL
B17: Quanto Investir por Mês? | D17: 200
B18: Por Quantos Anos? | D18: 5
B19: Taxa de Rendimento mensal? | D19: 0.01079
B20: Patrimônio acumulado? | D20: =FV(taxa_mensal,qntd_anos*12,aporte*-1) -> 16755.383
B21: Dividêndos Mensais? | D21: =patrimonio*rendimento_carteira -> 100.5323
B23: Cenários | D23: DIVIDENDO
A24: 2 | B24: Quanto em 2 Anos? | C24: =FV($D$19,$A24*12,$D$17*-1) -> 5445.5255 | D24: =C24*rendimento_carteira -> 32.673153
A25: 5 | B25: Quanto em 5 Anos? | C25: =FV($D$19,$A25*12,$D$17*-1) -> 16755.383 | D25: =C25*rendimento_carteira -> 100.5323
A26: 10 | B26: Quanto em 10 Anos? | C26: =FV($D$19,$A26*12,$D$17*-1) -> 48656.843 | D26: =C26*rendimento_carteira -> 291.94106
A27: 20 | B27: Quanto em 20 Anos? | C27: =FV($D$19,$A27*12,$D$17*-1) -> 225039.68 | D27: =C27*rendimento_carteira -> 1350.2381
A28: 30 | B28: Quanto em 30 Anos? | C28: =FV($D$19,$A28*12,$D$17*-1) -> 864433.93 | D28: =C28*rendimento_carteira -> 5186.6036
B30: PERFIL | C30: CONSERVADOR
B31: VALOR A SER INVESTIDO POR MÊS | C31: =aporte -> 200
B35: TIPOS DE FII | C35: PERCENTUAL SUGERIDO | D35: VALORES
B36: PAPEL | C36: =VLOOKUP($C$30&"-"&B36,'PLANILHA DE CONTROLE'!$A:$D,4,FALSE) -> 0.3 | D36: =C36*$C$31 -> 60
B37: TIJOLO | C37: =VLOOKUP($C$30&"-"&B37,'PLANILHA DE CONTROLE'!$A:$D,4,FALSE) -> 0.5 | D37: =C37*$C$31 -> 100
B38: HÍBRIDOS | C38: =VLOOKUP($C$30&"-"&B38,'PLANILHA DE CONTROLE'!$A:$D,4,FALSE) -> 0.1 | D38: =C38*$C$31 -> 20
B39: FOFs | C39: =VLOOKUP($C$30&"-"&B39,'PLANILHA DE CONTROLE'!$A:$D,4,FALSE) -> 0.1 | D39: =C39*$C$31 -> 20
B40: DESENVOLVIMENTO | C40: =VLOOKUP($C$30&"-"&B40,'PLANILHA DE CONTROLE'!$A:$D,4,FALSE) -> 0 | D40: =C40*$C$31 -> 0
B41: HOTELARIAS | C41: =VLOOKUP($C$30&"-"&B41,'PLANILHA DE CONTROLE'!$A:$D,4,FALSE) -> 0 | D41: =C41*$C$31 -> 0
D42: =SUM(D36:D41) -> 200

Sheet PLANILHA DE CONTROLE
A3: CHAVE COMPOSTA | B3: PERFIL | C3: TIPO DE FII | D3: %
A4: =B4&"-"&C4 -> CONSERVADOR-PAPEL | B4: CONSERVADOR | C4: PAPEL | D4: 0.3 | H4: %
A5: =B5&"-"&C5 -> CONSERVADOR-TIJOLO | B5: CONSERVADOR | C5: TIJOLO | D5: 0.5 | G5: MODERADO-TIJOLO | H5: =VLOOKUP(G5,$A$2:$D$22,4,FALSE) -> 0.35
A6: =B6&"-"&C6 -> CONSERVADOR-HÍBRIDOS | B6: CONSERVADOR | C6: HÍBRIDOS | D6: 0.1
A7: =B7&"-"&C7 -> CONSERVADOR-FOFs | B7: CONSERVADOR | C7: FOFs | D7: 0.1
A8: =B8&"-"&C8 -> CONSERVADOR-DESENVOLVIMENTO | B8: CONSERVADOR | C8: DESENVOLVIMENTO | D8: 0
A9: =B9&"-"&C9 -> CONSERVADOR-HOTELARIAS | B9: CONSERVADOR | C9: HOTELARIAS | D9: 0
A10: =B10&"-"&C10 -> MODERADO-PAPEL | B10: MODERADO | C10: PAPEL | D10: 0.32
A11: =B11&"-"&C11 -> MODERADO-TIJOLO | B11: MODERADO | C11: TIJOLO | D11: 0.35
A12: =B12&"-"&C12 -> MODERADO-HÍBRIDOS | B12: MODERADO | C12: HÍBRIDOS | D12: 0.08
A13: =B13&"-"&C13 -> MODERADO-FOFs | B13: MODERADO | C13: FOFs | D13: 0.05
A14: =B14&"-"&C14 -> MODERADO-DESENVOLVIMENTO | B14: MODERADO | C14: DESENVOLVIMENTO | D14: 0.1
A15: =B15&"-"&C15 -> MODERADO-HOTELARIAS | B15: MODERADO | C15: HOTELARIAS | D15: 0.1
A16: =B16&"-"&C16 -> AGRESSIVO-PAPEL | B16: AGRESSIVO | C16: PAPEL | D16: 0.5
A17: =B17&"-"&C17 -> AGRESSIVO-TIJOLO | B17: AGRESSIVO | C17: TIJOLO | D17: 0.1
... A21: =B21&"-"&C21 -> AGRESSIVO-HOTELARIAS | B21: AGRESSIVO | C21: HOTELARIAS | D21: 0.1
